MANIFEST.in
README.md
__init__.py
setup.py
utils.py
graphyti/Configuration.py
graphyti/__init__.py
graphyti/graphyti.cpp
graphyti/test-config.py
graphyti.egg-info/PKG-INFO
graphyti.egg-info/SOURCES.txt
graphyti.egg-info/dependency_links.txt
graphyti.egg-info/top_level.txt
graphyti/Exceptions/__init__.py
graphyti/Exceptions/runtime.py
graphyti/src/flash-graph/FG_basic_types.h
graphyti/src/flash-graph/FG_vector.h
graphyti/src/flash-graph/FGlib.cpp
graphyti/src/flash-graph/FGlib.h
graphyti/src/flash-graph/bitmap.h
graphyti/src/flash-graph/fg_utils.cpp
graphyti/src/flash-graph/fg_utils.h
graphyti/src/flash-graph/graph_config.cpp
graphyti/src/flash-graph/graph_config.h
graphyti/src/flash-graph/graph_engine.cpp
graphyti/src/flash-graph/graph_engine.h
graphyti/src/flash-graph/graph_exception.h
graphyti/src/flash-graph/graph_file_header.h
graphyti/src/flash-graph/graph_index.h
graphyti/src/flash-graph/in_mem_storage.cpp
graphyti/src/flash-graph/in_mem_storage.h
graphyti/src/flash-graph/load_balancer.cpp
graphyti/src/flash-graph/load_balancer.h
graphyti/src/flash-graph/message_processor.cpp
graphyti/src/flash-graph/message_processor.h
graphyti/src/flash-graph/messaging.cpp
graphyti/src/flash-graph/messaging.h
graphyti/src/flash-graph/partitioner.cpp
graphyti/src/flash-graph/partitioner.h
graphyti/src/flash-graph/scan_pointer.h
graphyti/src/flash-graph/steal_state.h
graphyti/src/flash-graph/trace_logger.h
graphyti/src/flash-graph/ts_graph.cpp
graphyti/src/flash-graph/ts_graph.h
graphyti/src/flash-graph/utils.cpp
graphyti/src/flash-graph/utils.h
graphyti/src/flash-graph/vertex.cpp
graphyti/src/flash-graph/vertex.h
graphyti/src/flash-graph/vertex_compute.cpp
graphyti/src/flash-graph/vertex_compute.h
graphyti/src/flash-graph/vertex_index.cpp
graphyti/src/flash-graph/vertex_index.h
graphyti/src/flash-graph/vertex_index_constructor.cpp
graphyti/src/flash-graph/vertex_index_constructor.h
graphyti/src/flash-graph/vertex_index_reader.cpp
graphyti/src/flash-graph/vertex_index_reader.h
graphyti/src/flash-graph/vertex_pointer.h
graphyti/src/flash-graph/vertex_program.cpp
