Metadata-Version: 1.0
Name: graphyti
Version: 0.0.2
Summary: A parallel and scalable graph library built on FlashGraph
Home-page: https://github.com/flashxio/graphyti
Author: Disa Mhembere, Da Zheng
Author-email: disa@cs.jhu.edu
License: Apache License, Version 2.0
Keywords: graph parallel scalable machine-learning
Platform: UNKNOWN
